llmdataset/__init__.py
llmdataset/dataset/__init__.py
llmdataset/dataset/aquarat.py
llmdataset/dataset/arc.py
llmdataset/dataset/base.py
llmdataset/dataset/bigbench.py
llmdataset/dataset/bigbenchhard.py
llmdataset/dataset/csqa.py
llmdataset/dataset/gpqa.py
llmdataset/dataset/gsm8k.py
llmdataset/dataset/gsmhard.py
llmdataset/dataset/multiarith.py
llmdataset/dataset/strategyqa.py
llmdataset/dataset/svamp.py
llmdataset/dataset/wikitablequestions.py
llmdataset/main.py
llmdataset-1.0.0.dist-info/LICENSE
llmdataset-1.0.0.dist-info/METADATA
llmdataset-1.0.0.dist-info/WHEEL
llmdataset-1.0.0.dist-info/RECORD
