Metadata-Version: 2.1
Name: llmdataset
Version: 1.0.0
Summary: llm dataset
Author: toma tanaka
Author-email: ulti4929@gmail.com
Requires-Python: >=3.9,<4.0
Classifier: Programming Language :: Python :: 3
Classifier: Programming Language :: Python :: 3.9
Classifier: Programming Language :: Python :: 3.10
Classifier: Programming Language :: Python :: 3.11
Requires-Dist: datasets (>=2.16.1,<3.0.0)
